covmatest/__init__.py
covmatest/get_covmat.py
covmatest/utils.py
covmatest-0.4.2.dist-info/LICENSE
covmatest-0.4.2.dist-info/METADATA
covmatest-0.4.2.dist-info/WHEEL
covmatest-0.4.2.dist-info/top_level.txt
covmatest-0.4.2.dist-info/RECORD
