Metadata-Version: 2.2
Name: covmatest
Version: 0.4.2
Summary: Alpha Waves Dataset
Home-page: https://github.com/gcattan/covmatest
Author: Gregoire Cattan
Author-email: gcattan@hotmail.fr
License: Apache 2.0
Project-URL: Bug Reports, https://github.com/gcattan/covmatest/issues
Project-URL: Source, https://github.com/gcattan/covmatest/
Keywords: EEG neuroscience test covariance matrices
Platform: any
Classifier: Development Status :: 3 - Alpha
Classifier: Intended Audience :: Science/Research
Classifier: Topic :: Scientific/Engineering
Classifier: License :: OSI Approved
Classifier: Programming Language :: Python :: 3.7
Requires-Python: >=3.8
License-File: LICENSE
Requires-Dist: alphawaves==0.5
Provides-Extra: tests
Requires-Dist: pytest; extra == "tests"
Requires-Dist: flake8; extra == "tests"
Dynamic: author
Dynamic: author-email
Dynamic: classifier
Dynamic: description
Dynamic: description-content-type
Dynamic: home-page
Dynamic: keywords
Dynamic: license
Dynamic: platform
Dynamic: project-url
Dynamic: provides-extra
Dynamic: requires-dist
Dynamic: requires-python
Dynamic: summary
